pyfacerecall/__init__.py
pyfacerecall/__main__.py
pyfacerecall/_version.py
pyfacerecall/dataset_generator.py
pyfacerecall/face_detection_operation.py
pyfacerecall/face_recognition.py
pyfacerecall/model.py
pyfacerecall-1.0.0.dist-info/METADATA
pyfacerecall-1.0.0.dist-info/WHEEL
pyfacerecall-1.0.0.dist-info/top_level.txt
pyfacerecall-1.0.0.dist-info/RECORD
