Metadata-Version: 2.1
Name: pyfacerecall
Version: 1.0.0
Summary: A Machine Learning Python library for face recognition.
Home-page: https://github.com/iamatulsingh/pyfacerecall
Author: Atul Singh
Author-email: atulsingh0401@gmail.com
Classifier: Programming Language :: Python :: 3
Classifier: License :: OSI Approved :: MIT License
Classifier: Operating System :: OS Independent
Requires-Python: >=3.8
Requires-Dist: imutils (==0.5.4)
Requires-Dist: matplotlib (==3.2.2)
Requires-Dist: mtcnn (==0.1.1)
Requires-Dist: numpy (==1.21.6)
Requires-Dist: opencv-python (==4.6.0.66)
Requires-Dist: opencv-contrib-python (==4.6.0.66)
Requires-Dist: Pillow (==9.3.0)
Requires-Dist: tensorflow (==2.9.2)
